AI2PY/__init__.py
AI2PY/main.py
ai2py-0.1.1.dist-info/METADATA
ai2py-0.1.1.dist-info/WHEEL
ai2py-0.1.1.dist-info/top_level.txt
ai2py-0.1.1.dist-info/RECORD
