Metadata-Version: 2.1
Name: ai2py
Version: 0.1.1
Summary: Integrate AI into Python projects easily.
Author: Bertran Usher (theaihub)
Author-email: <bjusher820@gmail.com>
Keywords: python,openai,ai,artificial intelligence
Classifier: Development Status :: 1 - Planning
Classifier: Intended Audience :: Developers
Classifier: Programming Language :: Python :: 3
Classifier: Operating System :: Unix
Classifier: Operating System :: MacOS :: MacOS X
Classifier: Operating System :: Microsoft :: Windows
Requires-Dist: openai
Requires-Dist: datetime
Requires-Dist: Pillow
